{
  "meta": {
    "title": "Curso internacional en Creación de Recursos Adaptados a través de las TIC en el Aula (PRODIS)",
    "description": "",
    "keywords": ""
  },
  "sections": {
    "head": {
      "title": "Curso internacional en Creación de Recursos Adaptados a través de las TIC en el Aula ",
      "image": {
        "alt": "imagen",
        "src": "https://assets.staging.bedu.org/UTEG/extension_universitaria_PRODIS_SAAC_desk_4c5f13bc33.jpg"
      },
      "description": "Imparte Instituto de Formación Inclusiva i360 de Fundación Prodis\n\nDuración aproximada: 100 horas (100% online)\n\nPerfil del participante: El curso está pensado tanto para profesionales en activo como para futuros: Maestros de educación Primaria e Infantil, Maestros de Educación Especial (PT y AL), Profesores de Educación Secundaria, Educadores sociales , Técnicos educativos, Orientadores, psicólogos, pedagogos y psicopedagogos, Otros profesionales de la educación.\n\nCarreras afines: Cualquier carrera o máster relacionado\n\nObjetivo: El curso tiene como objetivo principal promover el uso de las nuevas tecnologías en los entornos de enseñanza-aprendizaje de cara a generar contenidos adaptados y diversificados, que potencien la atención y la motivación del grupo de clase.\n\nTemas a abordar: \n\n Fundamentos teóricos sobre la importancia de las competencias digitales en la educación \n\n 1.- Inclusión de las TIC’s en el aula. \n\n 2.- TIC’s y aprendizaje colaborativo. \n\n 3.- TIC’ y aprendizaje significativo. \n\n 4.- El Diseño Universal del Aprendizaje y su relación con las TICs \n\n 5.- Principios generales de la lectura fácil.\n\n Ge-stión del aula virtual con herramientas de Google \n\n 1.- Introducción al entorno Google \n\n 2.- Google Classroom \n\n 3.- Google Calendar \n\n 4.- Google Drive \n\n 5.- Google formularios \n\n 6.- Google lens \n\n 7.- Presentaciones \n\n 8.- Documentos\n\n 9.- Hojas de cálculo \n\n 10-. Gmail Diseño y creación de contenidos adaptados\n\n 1.- Introducción al diseño y creación de contenidos adaptados \n\n 2.- Canva \n\n 3.- Prezi \n\n 4.- Clipchamp \n\n 5.- Wix \n\n 6.- Mapas mentales (Coggle, creately y popplet) \n\n 7.- Genially \n\n 8.- Kahoot \n\n 9.- Padlet \n\n 10-. Trello Videollamadas en la gestión de grupos de clase\n\n 1.- Pautas para la incorporación adecuada de recursos de videollamadas en la educación \n\n 2.- Zoom \n\n 3.- Meet \n\n 4.- Teams \n\n 5.- Slack\n\nRecursos de aprendizaje: \n\n 1. Online \n\n2. Cada bloque de contenido está compuesto por:\n\n • Manual en PDF\n\n • Videotutoriales\n\n • Vídeos grabados en entornos naturales donde observarás in situ la metodología propuesta.\n\n • Autoevalución\n\nEvaluación: La evaluación será llevará a cabo a través de una actividad final que denominamos reto en la que pondrás en práctica lo aprendido durante el curso.",
      "price": "$ 3,670.00",
      "textLink": {
        "description": "Solicita información en el siguiente correo:",
        "href": "mailto:extension@uteg.edu.mx",
        "text": "extension@uteg.edu.mx",
        "target": "__blank"
      }
    },
    "relatedCourses": {
      "title": "Cursos relacionados",
      "courses": [
        {
          "id": "123",
          "title": "Análisis de datos",
          "link": {
            "text": "Ver más",
            "size": "large",
            "isBold": false,
            "disabled": false,
            "id": "",
            "icon": "arrow_forward"
          },
          "image": {
            "desk": {
              "alt": "imagen",
              "src": "https://img.freepik.com/premium-photo/group-happy-young-students-university_85574-4531.jpg?w=2000"
            },
            "mobile": {
              "alt": "imagen",
              "src": "https://img.freepik.com/premium-photo/group-happy-young-students-university_85574-4531.jpg?w=2000g"
            }
          },
          "redirect": "oferta-educativa"
        },
        {
          "id": "123",
          "title": "Derecho de Autor y Propiedad Intelectual",
          "link": {
            "text": "Ver más",
            "size": "large",
            "isBold": false,
            "disabled": false,
            "id": "",
            "icon": ""
          },
          "image": {
            "desk": {
              "alt": "imagen",
              "src": "https://img.freepik.com/premium-photo/group-happy-young-students-university_85574-4531.jpg?w=2000"
            },
            "mobile": {
              "alt": "imagen",
              "src": "https://img.freepik.com/premium-photo/group-happy-young-students-university_85574-4531.jpg?w=2000g"
            }
          },
          "redirect": "oferta-educativa"
        },
        {
          "id": "123",
          "title": "Estrategias de tiendas en línea",
          "link": {
            "text": "Ver más",
            "size": "large",
            "isBold": false,
            "disabled": false,
            "id": "",
            "icon": ""
          },
          "image": {
            "desk": {
              "alt": "imagen",
              "src": "https://img.freepik.com/premium-photo/group-happy-young-students-university_85574-4531.jpg?w=2000"
            },
            "mobile": {
              "alt": "imagen",
              "src": "https://img.freepik.com/premium-photo/group-happy-young-students-university_85574-4531.jpg?w=2000g"
            }
          },
          "redirect": "oferta-educativa"
        },
        {
          "id": "123",
          "title": "Mega tendencias Globales",
          "link": {
            "text": "Ver más",
            "size": "large",
            "isBold": false,
            "disabled": false,
            "id": "",
            "icon": ""
          },
          "image": {
            "desk": {
              "alt": "imagen",
              "src": "https://img.freepik.com/premium-photo/group-happy-young-students-university_85574-4531.jpg?w=2000"
            },
            "mobile": {
              "alt": "imagen",
              "src": "https://img.freepik.com/premium-photo/group-happy-young-students-university_85574-4531.jpg?w=2000g"
            }
          },
          "redirect": "oferta-educativa"
        }
      ]
    }
  }
}
